dateutils/__init__.py
dateutils/_enums.py
dateutils/_implementation.py
dateutils/types.py
squirrels/__init__.py
squirrels/_api_server.py
squirrels/_auth.py
squirrels/_command_line.py
squirrels/_compile_prompts.py
squirrels/_connection_set.py
squirrels/_constants.py
squirrels/_dashboards.py
squirrels/_data_sources.py
squirrels/_dataset_types.py
squirrels/_env_vars.py
squirrels/_exceptions.py
squirrels/_initializer.py
squirrels/_logging.py
squirrels/_manifest.py
squirrels/_mcp_server.py
squirrels/_model_builder.py
squirrels/_model_configs.py
squirrels/_model_queries.py
squirrels/_models.py
squirrels/_package_loader.py
squirrels/_parameter_configs.py
squirrels/_parameter_options.py
squirrels/_parameter_sets.py
squirrels/_parameters.py
squirrels/_project.py
squirrels/_py_module.py
squirrels/_request_context.py
squirrels/_seeds.py
squirrels/_sources.py
squirrels/_utils.py
squirrels/_version.py
squirrels/arguments.py
squirrels/auth.py
squirrels/connections.py
squirrels/dashboards.py
squirrels/data_sources.py
squirrels/parameter_options.py
squirrels/parameters.py
squirrels/types.py
squirrels/_api_routes/__init__.py
squirrels/_api_routes/auth.py
squirrels/_api_routes/base.py
squirrels/_api_routes/dashboards.py
squirrels/_api_routes/data_management.py
squirrels/_api_routes/datasets.py
squirrels/_api_routes/oauth2.py
squirrels/_api_routes/project.py
squirrels/_arguments/__init__.py
squirrels/_arguments/init_time_args.py
squirrels/_arguments/run_time_args.py
squirrels/_package_data/base_project/.env
squirrels/_package_data/base_project/.env.example
squirrels/_package_data/base_project/connections.yml
squirrels/_package_data/base_project/duckdb_init.sql
squirrels/_package_data/base_project/gitignore
squirrels/_package_data/base_project/parameters.yml
squirrels/_package_data/base_project/squirrels.yml.j2
squirrels/_package_data/base_project/assets/expenses.db
squirrels/_package_data/base_project/assets/weather.db
squirrels-0.5.4.dist-info/METADATA
squirrels-0.5.4.dist-info/WHEEL
squirrels-0.5.4.dist-info/entry_points.txt
squirrels-0.5.4.dist-info/licenses/LICENSE
squirrels-0.5.4.dist-info/RECORD
