Metadata-Version: 2.4
Name: squirrels
Version: 0.5.4
Summary: Squirrels - API Framework for Data Analytics
Project-URL: Homepage, https://docs.pysquirrels.com
Project-URL: Repository, https://github.com/squirrels-analytics/squirrels
Project-URL: Documentation, https://docs.pysquirrels.com
Author-email: Tim Huang <timhuang95@gmail.com>
License-Expression: Apache-2.0
License-File: LICENSE
Classifier: Intended Audience :: Developers
Classifier: Topic :: Software Development :: Libraries :: Application Frameworks
Classifier: Topic :: Software Development :: Libraries :: Python Modules
Classifier: Typing :: Typed
Requires-Python: >=3.10
Requires-Dist: authlib>=1.5.2
Requires-Dist: bcrypt>=4.0.1
Requires-Dist: cachetools>=5.3.2
Requires-Dist: duckdb>=1.4.0
Requires-Dist: fastapi>=0.112.1
Requires-Dist: gitpython>=3.1.41
Requires-Dist: inquirer>=3.2.1
Requires-Dist: itsdangerous>=2.2.0
Requires-Dist: jinja2>=3.1.3
Requires-Dist: libpass>=1.9.0
Requires-Dist: matplotlib>=3.8.3
Requires-Dist: mcp>=1.24.0
Requires-Dist: pandas>=2.1.4
Requires-Dist: polars>=1.14.0
Requires-Dist: pyarrow>=19.0.1
Requires-Dist: pydantic>=2.8.2
Requires-Dist: pyjwt>=2.8.0
Requires-Dist: python-dotenv>=1.0.1
Requires-Dist: python-multipart>=0.0.9
Requires-Dist: pyyaml>=6.0.1
Requires-Dist: sqlalchemy>=2.0.25
Requires-Dist: sqlglot>=26.12.1
Requires-Dist: uvicorn>=0.30.6
